flake8_django_on_delete_comment/__init__.py
flake8_django_on_delete_comment/ast_helpers.py
flake8_django_on_delete_comment/checker.py
flake8_django_on_delete_comment-0.0.3.dist-info/LICENSE
flake8_django_on_delete_comment-0.0.3.dist-info/METADATA
flake8_django_on_delete_comment-0.0.3.dist-info/WHEEL
flake8_django_on_delete_comment-0.0.3.dist-info/entry_points.txt
flake8_django_on_delete_comment-0.0.3.dist-info/top_level.txt
flake8_django_on_delete_comment-0.0.3.dist-info/RECORD
