Metadata-Version: 2.1
Name: flake8-django-on-delete-comment
Version: 0.0.3
Summary: A flake8 extension to validate django models ForeignKey fields on on_delete CASCADE comment
Home-page: https://github.com/best-doctor/flake8-django-on-delete-comment
Author: BestDoctor
Author-email: khkaterine@gmail.com
License: MIT
Keywords: flake8 on_delete
Platform: UNKNOWN
Classifier: Environment :: Console
Classifier: Framework :: Flake8
Classifier: Operating System :: OS Independent
Classifier: Topic :: Software Development :: Documentation
Classifier: Topic :: Software Development :: Libraries :: Python Modules
Classifier: Topic :: Software Development :: Quality Assurance
Classifier: Programming Language :: Python
Classifier: Programming Language :: Python :: 3.7
Classifier: Programming Language :: Python :: 3.8
Classifier: Programming Language :: Python :: 3.9
Classifier: Programming Language :: Python :: 3.10
Requires-Python: >=3.7
License-File: LICENSE
Requires-Dist: flake8
